selen_enchanted/__init__.py
selen_enchanted/agents/__init__.py
selen_enchanted/agents/info.py
selen_enchanted/agents/user_agency.py
selen_enchanted/components/__init__.py
selen_enchanted/components/actions.py
selen_enchanted/components/cookies.py
selen_enchanted/components/locator.py
selen_enchanted/components/scroller.py
selen_enchanted/components/tab.py
selen_enchanted/core/__init__.py
selen_enchanted/core/browser.py
selen_enchanted/core/driver.py
selen_enchanted/core/javascripts.py
selen_enchanted/core/options.py
selen_enchanted/utilities/__init__.py
selen_enchanted/utilities/decorators.py
selen_enchanted/utilities/exceptions.py
selen_enchanted/utilities/logger.py
selen_enchanted/utilities/meta_classes.py
selen_enchanted/utilities/profiler.py
selen_enchanted/utilities/sleeper.py
selen_enchanted-0.0.10.7.dist-info/METADATA
selen_enchanted-0.0.10.7.dist-info/WHEEL
selen_enchanted-0.0.10.7.dist-info/top_level.txt
selen_enchanted-0.0.10.7.dist-info/RECORD
