Metadata-Version: 2.4
Name: selen-enchanted
Version: 0.0.10.7
Summary: A selenium wrapper that makes it easier to use
Home-page: https://github.com/Andrew2077/SelenEnchanted
Author: Andrew Naaem
Author-email: andrew.naaem99@gmail.com
License: Apache License 2.0
Keywords: selenium,wrapper,automation,testing
Classifier: Programming Language :: Python :: 3.9
Classifier: License :: OSI Approved :: Apache Software License
Classifier: Operating System :: OS Independent
Requires-Dist: chromedriver-autoinstaller==0.6.2
Requires-Dist: requests==2.32.3
Requires-Dist: selenium==4.23.1
Requires-Dist: selenium-wire==5.1.0
Requires-Dist: ua-generator==0.5.1
Requires-Dist: user-agents==2.2.0
Requires-Dist: webdriver-manager==4.0.1
Requires-Dist: blinker==1.6.2
Requires-Dist: Pillow==11.0.0
Requires-Dist: numpy
Requires-Dist: structlog==23.1.0
Requires-Dist: numpy
Dynamic: author
Dynamic: author-email
Dynamic: classifier
Dynamic: description
Dynamic: description-content-type
Dynamic: home-page
Dynamic: keywords
Dynamic: license
Dynamic: requires-dist
Dynamic: summary
